datapackage/VERSION
datapackage/__init__.py
datapackage/__main__.py
datapackage/cli.py
datapackage/config.py
datapackage/exceptions.py
datapackage/group.py
datapackage/helpers.py
datapackage/infer.py
datapackage/package.py
datapackage/profile.py
datapackage/pushpull.py
datapackage/registry.py
datapackage/resource.py
datapackage/validate.py
datapackage/profiles/data-package.json
datapackage/profiles/data-resource.json
datapackage/profiles/fiscal-data-package.json
datapackage/profiles/registry.json
datapackage/profiles/tabular-data-package.json
datapackage/profiles/tabular-data-resource.json
datapackage-1.15.2.dist-info/LICENSE.md
datapackage-1.15.2.dist-info/METADATA
datapackage-1.15.2.dist-info/WHEEL
datapackage-1.15.2.dist-info/entry_points.txt
datapackage-1.15.2.dist-info/top_level.txt
datapackage-1.15.2.dist-info/RECORD
