Metadata-Version: 2.1
Name: datapackage
Version: 1.15.2
Summary: Utilities to work with Data Packages as defined on specs.frictionlessdata.io
Home-page: https://github.com/frictionlessdata/datapackage-py
Author: Open Knowledge Foundation
Author-email: info@okfn.org
License: MIT
Keywords: frictionless data,open data,json schema,table schema,data package,tabular data package
Platform: UNKNOWN
Classifier: Development Status :: 4 - Beta
Classifier: Intended Audience :: Developers
Classifier: Intended Audience :: Information Technology
Classifier: Topic :: Utilities
Classifier: License :: OSI Approved :: MIT License
Classifier: Programming Language :: Python :: 2.7
Classifier: Programming Language :: Python :: 3.4
Classifier: Programming Language :: Python :: 3.5
Classifier: Programming Language :: Python :: 3.6
Classifier: Programming Language :: Python :: 3.7
Provides-Extra: develop
Provides-Extra: cchardet
